    <revision>
      <id>588931668</id>
      <timestamp>2014-01-03T05:58:27Z</timestamp>
      <contributor>
        <username>Arms &amp; Hearts</username>
        <id>2687020</id>
      </contributor>
      <comment>[[WP:AES|←]]Redirected page to [[United States House of Representatives elections in Mississippi, 2010#District 4]]</comment>
      <text xml:space="preserve">#REDIRECT [[United States House of Representatives elections in Mississippi, 2010#District 4]]</text>
      <sha1>2v43290if6n1qw7wlq7jnglsxxghkoe</sha1>
      <model>wikitext</model>
      <format>text/x-wiki</format>
    </revision>
  </page>
  <page>
    <title>Compass Card (Translink)</title>
    <ns>0</ns>
    <id>41535294</id>
    <revision>
      <id>588931671</id>
      <timestamp>2014-01-03T05:58:30Z</timestamp>
      <contributor>
        <username>Dangodin</username>
        <id>20480636</id>
      </contributor>
      <comment>[[WP:AES|←]]Created page with '&lt;!-- INTRODUCTION --&gt;  '''Compass Card''', or '''Compass''', is an electronic payment system for public transit that is currently being deployed in Vancouver, BC...'</comment>
      <text xml:space="preserve">&lt;!-- INTRODUCTION --&gt;

'''Compass Card''', or '''Compass''', is an electronic payment system for public transit that is currently being deployed in Vancouver, BC. It is operated by [http://en.wikipedia.org/wiki/TransLink_(British_Columbia) TransLink] transportation authority. 

The project started in xxxx with completion originally scheduled for yyyy. Minor delays pushed the anticipated go live date to zzzzz.

Compass is a [https://en.wikipedia.org/wiki/Smart_card Smart Card]] based payment system, requiring users to pre purchase a card at one of the &lt;booths&gt; located at &lt;skytrain and ???&gt; and fill this card with credit. The &lt;booths&gt; support cash, credit, or debit.

==History==

==Usage==

==Cost==

==Controversy==

==References==</text>
      <sha1>b3b3woinhljajkagp4l7rt35haekrmo</sha1>
      <model>wikitext</model>
      <format>text/x-wiki</format>
    </revision>
  </page>
  <page>
    <title>Category:Mixed martial arts in North America</title>
    <ns>14</ns>
    <id>41535303</id>
    <revision>
      <id>588931943</id>
      <timestamp>2014-01-03T06:00:58Z</timestamp>
      <contributor>
        <username>Ianblair23</username>
        <id>145927</id>
      </contributor>
      <comment>created cat</comment>
      <text xml:space="preserve">[[Category:Mixed martial arts by continent|North America]]
[[Category:Martial arts in North America| Mixed martial arts]]</text>
      <sha1>h9945sauanfak2gtt9q9nchbr0ddnf8</sha1>
      <model>wikitext</model>
      <format>text/x-wiki</format>
    </revision>
  </page>
  <page>
    <title>Smith, Chad</title>
    <ns>0</ns>
    <id>41535304</id>
    <redirect title="Chad Smith" />
    <revision>
      <id>588931945</id>
      <timestamp>2014-01-03T06:00:59Z</timestamp>
      <contributor>
        <username>Hoops gza</username>
        <id>11079571</id>
      </contributor>
      <comment>[[WP:AES|←]]Redirected page to [[Chad Smith]]</comment>
      <text xml:space="preserve">#REDIRECT [[Chad Smith]]</text>
      <sha1>turl9ekdwwei9uy0jm38y1o63qtvyd5</sha1>
      <model>wikitext</model>
      <format>text/x-wiki</format>
    </revision>
  </page>
  <page>
    <title>Chadwick Gaylord &quot;Chad&quot; Smith</title>
    <ns>0</ns>
    <id>41535312</id>
    <redirect title="Chad Smith" />
    <revision>
      <id>588932032</id>
      <timestamp>2014-01-03T06:01:52Z</timestamp>
      <contributor>
        <username>Hoops gza</username>
        <id>11079571</id>
      </contributor>
      <comment>[[WP:AES|←]]Redirected page to [[Chad Smith]]</comment>
      <text xml:space="preserve">#REDIRECT [[Chad Smith]]</text>
      <sha1>turl9ekdwwei9uy0jm38y1o63qtvyd5</sha1>
      <model>wikitext</model>
      <format>text/x-wiki</format>
    </revision>
  </page>
  <page>
    <title>Smith, Chadwick Gaylord</title>
    <ns>0</ns>
    <id>41535317</id>
    <redirect title="Chad Smith" />
    <revision>
      <id>588932077</id>
      <timestamp>2014-01-03T06:02:14Z</timestamp>
      <contributor>
        <username>Hoops gza</username>
        <id>11079571</id>
      </contributor>
      <comment>[[WP:AES|←]]Redirected page to [[Chad Smith]]</comment>
      <text xml:space="preserve">#REDIRECT [[Chad Smith]]</text>
      <sha1>turl9ekdwwei9uy0jm38y1o63qtvyd5</sha1>
      <model>wikitext</model>
      <format>text/x-wiki</format>
    </revision>
  </page>
  <page>
    <title>Willkapanpa mountain range</title>
    <ns>0</ns>
    <id>41535319</id>
    <redirect title="Willkapampa mountain range" />
    <revision>
      <id>588932099</id>
      <timestamp>2014-01-03T06:02:21Z</timestamp>
      <contributor>
        <username>CaTi0604</username>
        <id>1509060</id>
      </contributor>
      <comment>[[WP:AES|←]]Redirected page to [[Willkapampa mountain range]]</comment>
      <text xml:space="preserve">#REDIRECT[[Willkapampa mountain range]]</text>
      <sha1>m2dpunmwgjp19zf2hyhy158r37nj098</sha1>
      <model>wikitext</model>
      <format>text/x-wiki</format>
    </revision>
  </page>
  <page>
    <title>Template:Fb competition 2014-15 QD2</title>
    <ns>10</ns>
    <id>41535321</id>
    <revision>
      <id>588932139</id>
      <timestamp>2014-01-03T06:02:38Z</timestamp>
      <contributor>
        <username>Weka</username>
        <id>1426266</id>
      </contributor>
      <comment>[[WP:AES|←]]Created page with '[[2014–15 Qatari 2nd Division]]'</comment>
      <text xml:space="preserve">[[2014–15 Qatari 2nd Division]]</text>
      <sha1>af4ji00w6puyda88zc379ycae5yqtqt</sha1>
      <model>wikitext</model>
      <format>text/x-wiki</format>
    </revision>
  </page>
  <page>
    <title>Smith, Chadwick Gaylord &quot;Chad&quot;</title>
    <ns>0</ns>
    <id>41535322</id>
    <redirect title="Chad Smith" />
    <revision>
      <id>588932141</id>
      <timestamp>2014-01-03T06:02:39Z</timestamp>
      <contributor>
        <username>Hoops gza</username>
        <id>11079571</id>
      </contributor>
      <comment>[[WP:AES|←]]Redirected page to [[Chad Smith]]</comment>
      <text xml:space="preserve">#REDIRECT [[Chad Smith]]</text>
      <sha1>turl9ekdwwei9uy0jm38y1o63qtvyd5</sha1>
      <model>wikitext</model>
      <format>text/x-wiki</format>
    </revision>
  </page>
  <page>
    <title>Category:Mixed martial arts in South America</title>
    <ns>14</ns>
    <id>41535323</id>
    <revision>
      <id>588932150</id>
      <timestamp>2014-01-03T06:02:45Z</timestamp>
      <contributor>
        <username>Ianblair23</username>
        <id>145927</id>
      </contributor>
      <comment>created cat</comment>
      <text xml:space="preserve">[[Category:Mixed martial arts by continent|South America]]
[[Category:Martial arts in South America| Mixed martial arts]]</text>
      <sha1>45in1e4wqoiz3uy7qz671gaick9n0b6</sha1>
      <model>wikitext</model>
      <format>text/x-wiki</format>
    </revision>
  </page>
  <page>
    <title>Urupanpa mountain range</title>
    <ns>0</ns>
    <id>41535324</id>
    <redirect title="Urupampa mountain range" />
    <revision>
      <id>588932164</id>
      <timestamp>2014-01-03T06:02:52Z</timestamp>
      <contributor>
        <username>CaTi0604</username>
        <id>1509060</id>
      </contributor>
      <comment>[[WP:AES|←]]Redirected page to [[Urupampa mountain range]]</comment>
      <text xml:space="preserve">#REDIRECT[[Urupampa mountain range]]</text>
      <sha1>3hflabt4nemrnutsytwc0waby0u1b5t</sha1>
      <model>wikitext</model>
      <format>text/x-wiki</format>
    </revision>
  </page>
  <page>
    <title>Confia em Mim</title>
    <ns>0</ns>
    <id>41535325</id>
    <revision>
      <id>588932622</id>
      <parentid>588932223</parentid>
      <timestamp>2014-01-03T06:06:54Z</timestamp>
      <contributor>
        <username>Flaviohmg</username>
        <id>854326</id>
      </contributor>
      <text xml:space="preserve">{{Infobox film
| name           = Confia em Mim
| image          = Confia em Mim.jpg
| caption        = Theatrical release poster
| director       = Michel Tikhomiroff
| producer       = 
| screenplay     = Fabio Danesi
| based on       = 
| starring       = [[Mateus Solano]] &lt;br /&gt; Fernanda Machado &lt;br /&gt; Bruno Giordano &lt;br /&gt; Fernanda D`Umbra
| music          = 
| cinematography = 
| editing        = 
| studio         = Globo Filmes&lt;br&gt; Mixer|
| distributor    = [[Downtown Filmes]]
| released       = {{film date|2014|3|28|Brazil}}
| runtime        = 
| country        = Brazil
| language       = Portuguese
| budget         =
| gross          = 
}}


'''''Confia em Mim''''' is a 2014 Brazilian [[Thriller|thriller film]] directed by Michel Tikhomiroff. It is the first feature film directed by  Tikhomiroff.&lt;ref&gt;{{cite web | url=http://www.adorocinema.com/filmes/filme-210851/curiosidades/ | title=Confia em Mim | publisher=Adoro Cinema | accessdate=3 January 2014}}&lt;/ref&gt;

==Plot==
Mari, a promising chef, works hard to save her economies to open her own restaurant. Recently separated she now engages with Caio, an investor who will help her to realize her dream. However things won't be easy as she thinks.&lt;ref&gt;{{cite web | url=http://www.interfilmes.com/filme_28611_Confia.em.Mim-(Confia.em.Mim).html | title=Confia em Mim | publisher=InterFilmes | accessdate=3 January 2014}}&lt;/ref&gt;

== Cast ==
* [[Mateus Solano]] as Caio 
* Fernanda Machado as Mari
* Bruno Giordano as Vicente 
* Fernanda D'Umbra as Teresa

==References==
{{Reflist}}

==External links==
* {{IMDb title|2363349|Confia em Mim}}

[[Category:Brazilian films]]
[[Category:Brazilian thriller films]]
[[Category:2010s thriller films]]
 
[[pt:Confia em Mim (filme)]]</text>
      <sha1>m6r64dfl4ongbmlndyol0tcdsjj8j66</sha1>
      <model>wikitext</model>
      <format>text/x-wiki</format>
    </revision>
  </page>
  <page>
    <title>Three Mile Harbor, New York</title>
    <ns>0</ns>
    <id>41535327</id>
    <redirect title="Springs, New York" />
    <revision>
      <id>588932256</id>
      <timestamp>2014-01-03T06:03:50Z</timestamp>
      <contributor>
        <username>C16sh</username>
        <id>11899613</id>
      </contributor>
      <comment>[[WP:AES|←]]Redirected page to [[Springs, New York]]</comment>
      <text xml:space="preserve">#REDIRECT [[Springs, New York]]</text>
      <sha1>26042u7qum1lz0dx1sy0um2xma5dyjy</sha1>
      <model>wikitext</model>
      <format>text/x-wiki</format>
    </revision>
  </page>
  <page>
    <title>Klinghoffer (surname)</title>
    <ns>0</ns>
    <id>41535328</id>
    <redirect title="Klinghoffer" />
    <revision>
      <id>588932257</id>
      <timestamp>2014-01-03T06:03:50Z</timestamp>
      <contributor>
        <username>Hoops gza</username>
        <id>11079571</id>
      </contributor>
      <comment>[[WP:AES|←]]Redirected page to [[Klinghoffer]]</comment>
      <text xml:space="preserve">#REDIRECT [[Klinghoffer]]</text>
      <sha1>1ecxnbvs7kmr3q6pclntas8743z2hmn</sha1>
      <model>wikitext</model>
      <format>text/x-wiki</format>
    </revision>
  </page>
  <page>
    <title>Template:Square tiling tessellations</title>
    <ns>10</ns>
    <id>41535329</id>
    <revision>
      <id>588932511</id>
      <parentid>588932439</parentid>
      <timestamp>2014-01-03T06:06:00Z</timestamp>
      <contributor>
        <username>Tomruen</username>
        <id>63601</id>
      </contributor>
      <text xml:space="preserve">{| class=wikitable
|+ {4,4,p}
|-
!Space
!E&lt;sup&gt;3&lt;/sup&gt;
!colspan=3|[[hyperbolic space|H&lt;sup&gt;3&lt;/sup&gt;]]
|- align=center
!Name
!{4,4,2}&lt;BR&gt;{{CDD|node_1|4|node|4|node|2|node}}
![[Square tiling honeycomb|{4,4,3}]]&lt;BR&gt;{{CDD|node_1|4|node|4|node|3|node}}
![[Order-4 square tiling honeycomb|{4,4,4}]]&lt;BR&gt;{{CDD|node_1|4|node|4|node|4|node}}
!... [[Infinite-order square tiling honeycomb|{4,4,&amp;infin;}]]&lt;BR&gt;{{CDD|node_1|4|node|4|node|infin|node}}
|- align=center
!Image
|
|[[File:H3 443 FC boundary.png|100px]]
|[[File:H3 444 FC boundary.png|100px]]
|
|- align=center
!Vertex figure
|valign=bottom|[[Dihedron|{4,2}]]&lt;BR&gt;{{CDD|node_1|2|node|4|node}}
|[[File:Hexahedron.png|100px]]&lt;BR&gt;[[Cube|{4,3}]]&lt;BR&gt;{{CDD|node_1|4|node|3|node}}
|[[File:Square_tiling_uniform_coloring_1.png|100px]]&lt;BR&gt;[[Square tiling|{4,4}]]&lt;BR&gt;{{CDD|node_1|4|node|4|node}}
|[[File:H2_tiling_24i-4.png|100px]]&lt;BR&gt;[[Infinite-order square tiling|{4,&amp;infin;}]]&lt;BR&gt;{{CDD|node_1|4|node|infin|node}}
|}</text>
      <sha1>6grwjnfoikuiy36yz85wuef5vbxcujs</sha1>
      <model>wikitext</model>
      <format>text/x-wiki</format>
    </revision>
  </page>
  <page>
    <title>Klinghoffer (disambiguation)</title>
    <ns>0</ns>
    <id>41535332</id>
    <redirect title="Klinghoffer" />
    <revision>
      <id>588932301</id>
      <timestamp>2014-01-03T06:04:10Z</timestamp>
      <contributor>
        <username>Hoops gza</username>
        <id>11079571</id>
      </contributor>
      <comment>[[WP:AES|←]]Redirected page to [[Klinghoffer]]</comment>
      <text xml:space="preserve">#REDIRECT [[Klinghoffer]]</text>
      <sha1>1ecxnbvs7kmr3q6pclntas8743z2hmn</sha1>
      <model>wikitext</model>
      <format>text/x-wiki</format>
    </revision>
  </page>
  <page>
    <title>Anna Jewel Revies</title>
    <ns>0</ns>
    <id>41535333</id>
    <redirect title="United States House of Representatives elections in Mississippi, 2010" />
    <revision>
      <id>588932314</id>
      <timestamp>2014-01-03T06:04:16Z</timestamp>
      <contributor>
        <username>Arms &amp; Hearts</username>
        <id>2687020</id>
      </contributor>
      <comment>[[WP:AES|←]]Redirected page to [[United States House of Representatives elections in Mississippi, 2010#District 4]]</comment>
      <text xml:space="preserve">#REDIRECT [[United States House of Representatives elections in Mississippi, 2010#District 4]]</text>
      <sha1>2v43290if6n1qw7wlq7jnglsxxghkoe</sha1>
      <model>wikitext</model>
      <format>text/x-wiki</format>
    </revision>
  </page>
  <page>
    <title>Josh Adam Klinghoffer</title>
    <ns>0</ns>
    <id>41535336</id>
    <redirect title="Josh Klinghoffer" />
    <revision>
      <id>588932348</id>
      <timestamp>2014-01-03T06:04:31Z</timestamp>
      <contributor>
        <username>Hoops gza</username>
        <id>11079571</id>
      </contributor>
      <comment>[[WP:AES|←]]Redirected page to [[Josh Klinghoffer]]</comment>
      <text xml:space="preserve">#REDIRECT [[Josh Klinghoffer]]</text>
      <sha1>40kwf2kyrdbsrwz3d45aik31h41obsq</sha1>
      <model>wikitext</model>
      <format>text/x-wiki</format>
    </revision>
  </page>
  <page>
    <title>Khirkiqocha</title>
    <ns>0</ns>
    <id>41535338</id>
    <redirect title="Khirkiqucha" />
    <revision>
      <id>588932363</id>
      <timestamp>2014-01-03T06:04:41Z</timestamp>
      <contributor>
        <username>CaTi0604</username>
        <id>1509060</id>
      </contributor>
      <comment>[[WP:AES|←]]Redirected page to [[Khirkiqucha]]</comment>
      <text xml:space="preserve">#REDIRECT[[Khirkiqucha]]</text>
      <sha1>k1zneikb0kq2hul4bn1wjdfl0dqbavi</sha1>
      <model>wikitext</model>
      <format>text/x-wiki</format>
    </revision>
  </page>
  <page>
    <title>Category:Mixed martial arts in Oceania</title>
    <ns>14</ns>
    <id>41535339</id>
    <revision>
      <id>588932364</id>
      <timestamp>2014-01-03T06:04:42Z</timestamp>
      <contributor>
        <username>Ianblair23</username>
        <id>145927</id>
      </contributor>
      <comment>created cat</comment>
      <text xml:space="preserve">[[Category:Mixed martial arts by continent|Oceania]]
[[Category:Martial arts in Oceania| Mixed martial arts]]</text>
      <sha1>6ytp5veimhyd9vxc4c8fnybjw3jkw8c</sha1>
      <model>wikitext</model>
      <format>text/x-wiki</format>
    </revision>
  </page>
  <page>
    <title>Klinghoffer, Josh Adam</title>
    <ns>0</ns>
    <id>41535340</id>
    <redirect title="Josh Klinghoffer" />
    <revision>
      <id>588932387</id>
      <timestamp>2014-01-03T06:04:51Z</timestamp>
      <contributor>
        <username>Hoops gza</username>
        <id>11079571</id>
      </contributor>
      <comment>[[WP:AES|←]]Redirected page to [[Josh Klinghoffer]]</comment>
      <text xml:space="preserve">#REDIRECT [[Josh Klinghoffer]]</text>
      <sha1>40kwf2kyrdbsrwz3d45aik31h41obsq</sha1>
      <model>wikitext</model>
      <format>text/x-wiki</format>
    </revision>
  </page>
  <page>
    <title>Klinghoffer, Josh</title>
    <ns>0</ns>
    <id>41535341</id>
    <redirect title="Josh Klinghoffer" />
    <revision>
      <id>588932429</id>
      <timestamp>2014-01-03T06:05:12Z</timestamp>
      <contributor>
        <username>Hoops gza</username>
        <id>11079571</id>
      </contributor>
      <comment>[[WP:AES|←]]Redirected page to [[Josh Klinghoffer]]</comment>
      <text xml:space="preserve">#REDIRECT [[Josh Klinghoffer]]</text>
      <sha1>40kwf2kyrdbsrwz3d45aik31h41obsq</sha1>
      <model>wikitext</model>
      <format>text/x-wiki</format>
    </revision>
  </page>
  <page>
    <title>Killaqocha</title>
    <ns>0</ns>
    <id>41535342</id>
    <redirect title="Killaqucha" />
    <revision>
      <id>588932442</id>
      <timestamp>2014-01-03T06:05:20Z</timestamp>
      <contributor>
        <username>CaTi0604</username>
        <id>1509060</id>
      </contributor>
      <comment>[[WP:AES|←]]Redirected page to [[Killaqucha]]</comment>
      <text xml:space="preserve">#REDIRECT[[Killaqucha]]</text>
      <sha1>4nulxy1k56ou7ue3ibw6ij4a6z1kx26</sha1>
      <model>wikitext</model>
      <format>text/x-wiki</format>
    </revision>
  </page>
  <page>
    <title>Josh Klinghofer</title>
    <ns>0</ns>
    <id>41535343</id>
    <redirect title="Josh Klinghoffer" />
    <revision>
      <id>588932452</id>
      <timestamp>2014-01-03T06:05:27Z</timestamp>
      <contributor>
        <username>Hoops gza</username>
        <id>11079571</id>
      </contributor>
      <comment>[[WP:AES|←]]Redirected page to [[Josh Klinghoffer]]</comment>
      <text xml:space="preserve">#REDIRECT [[Josh Klinghoffer]]</text>
      <sha1>40kwf2kyrdbsrwz3d45aik31h41obsq</sha1>
      <model>wikitext</model>
      <format>text/x-wiki</format>
    </revision>
  </page>
  <page>
    <title>Josh Adam Klinghofer</title>
    <ns>0</ns>
    <id>41535347</id>
    <redirect title="Josh Klinghoffer" />
    <revision>
      <id>588932481</id>
      <timestamp>2014-01-03T06:05:43Z</timestamp>
      <contributor>
        <username>Hoops gza</username>
        <id>11079571</id>
      </contributor>
      <comment>[[WP:AES|←]]Redirected page to [[Josh Klinghoffer]]</comment>
      <text xml:space="preserve">#REDIRECT [[Josh Klinghoffer]]</text>
      <sha1>40kwf2kyrdbsrwz3d45aik31h41obsq</sha1>
      <model>wikitext</model>
      <format>text/x-wiki</format>
    </revision>
  </page>
  <page>
    <title>Klinghofer, Josh</title>
    <ns>0</ns>
    <id>41535348</id>
    <redirect title="Josh Klinghoffer" />
    <revision>
      <id>588932506</id>
      <timestamp>2014-01-03T06:05:58Z</timestamp>
      <contributor>
        <username>Hoops gza</username>
        <id>11079571</id>
      </contributor>
      <comment>[[WP:AES|←]]Redirected page to [[Josh Klinghoffer]]</comment>
      <text xml:space="preserve">#REDIRECT [[Josh Klinghoffer]]</text>
      <sha1>40kwf2kyrdbsrwz3d45aik31h41obsq</sha1>
      <model>wikitext</model>
      <format>text/x-wiki</format>
    </revision>
  </page>
  <page>
    <title>Klinghofer, Josh Adam</title>
    <ns>0</ns>
    <id>41535350</id>
    <redirect title="Josh Klinghoffer" />
    <revision>
      <id>588932541</id>
      <timestamp>2014-01-03T06:06:12Z</timestamp>
      <contributor>
        <username>Hoops gza</username>
        <id>11079571</id>
      </contributor>
      <comment>[[WP:AES|←]]Redirected page to [[Josh Klinghoffer]]</comment>
      <text xml:space="preserve">#REDIRECT [[Josh Klinghoffer]]</text>
      <sha1>40kwf2kyrdbsrwz3d45aik31h41obsq</sha1>
      <model>wikitext</model>
      <format>text/x-wiki</format>
    </revision>
  </page>
  <page>
    <title>Transfast</title>
    <ns>0</ns>
    <id>41535353</id>
    <revision>
      <id>588932772</id>
      <parentid>588932559</parentid>
      <timestamp>2014-01-03T06:08:15Z</timestamp>
      <contributor>
        <username>VIJITHKAMATH</username>
        <id>20481245</id>
      </contributor>
      <text xml:space="preserve">[http://www.transfast.com www.transfast.com]

About Us

About Trans-Fast
Since 1988, Trans-Fast has provided its customers a reliable and affordable way of sending money to their families and friends. Our mission is to provide the most secure, fast, affordable and convenient way of sending money worldwide, anytime of the day or night. In addition to an extensive and ever growing network of agents in the U.S. and around the world, we have established an online presence. Our agent network, built over the last two decades, includes over a hundred thousand points of payment around the world.


With Trans-Fast your loved ones back home have choices, they can pick-up their remittance in cash, receive it directly into their bank account, and receive money via many other convenient options.

Having operated as a licensed money transfer company in the United States for over two decades, Trans-Fast adheres to the highest compliance and safety standards. In our 22 years in the money transfer business our customers have trusted and relied upon us to provide a high quality service.

We understand how important each and every transfer is to our customers and are committed to earning your business. We are expanding our online services to a growing list of countries, so please check back again if your country of choice is not yet offered.

Learn more about how to transfer money worldwide with Trans-Fast or refer to our Frequently Asked Questions (FAQ).

Questions, notifications, requests for refunds or further information can be sent to Trans-Fast, as follows: online, by telephone at 1-888-973-6383; or by mail at Trans-Fast Remittance LLC, attn: Customer Service, 44 Wall Street, Ste. 400, New York, NY 10005, USA.

For general information feel free to contact us.</text>
      <sha1>5x3eie9yb9ujpin13dda6tevtkuegvr</sha1>
      <model>wikitext</model>
      <format>text/x-wiki</format>
    </revision>
  </page>
  <page>
    <title>Anna Revies</title>
    <ns>0</ns>
    <id>41535354</id>
    <redirect title="United States House of Representatives elections in Mississippi, 2010" />
    <revision>
      <id>588932560</id>
      <timestamp>2014-01-03T06:06:22Z</timestamp>
      <contributor>
        <username>Arms &amp; Hearts</username>
        <id>2687020</id>
      </contributor>
      <comment>[[WP:AES|←]]Redirected page to [[United States House of Representatives elections in Mississippi, 2010#District 4]]</comment>
      <text xml:space="preserve">#REDIRECT [[United States House of Representatives elections in Mississippi, 2010#District 4]]</text>
      <sha1>2v43290if6n1qw7wlq7jnglsxxghkoe</sha1>
      <model>wikitext</model>
      <format>text/x-wiki</format>
    </revision>
  </page>
  <page>
    <title>File:Confia em Mim.jpg</title>
    <ns>6</ns>
    <id>41535355</id>
    <revision>
      <id>588932563</id>
      <timestamp>2014-01-03T06:06:24Z</timestamp>
      <contributor>
        <username>Flaviohmg</username>
        <id>854326</id>
      </contributor>
      <comment>Uploading a piece of non-free cover art using [[Wikipedia:File_Upload_Wizard|File Upload Wizard]]</comment>
      <text xml:space="preserve">==Summary==
{{Non-free use rationale 2
|Description = This is a poster for Confia em Mim.
|Source = http://globofilmes.globo.com/ConfiaemMim/
|Author = The poster art copyright is believed to belong to the distributor of the film, the publisher of the film or the graphic artist.
|Article = Confia em Mim
|Purpose = to serve as the primary means of visual identification at the top of the article dedicated to the work in question.
|Replaceability = n.a.
|Minimality = To illustrate promotional material used for the movie in question.
|Commercial = n.a.
}}

==Licensing==
{{Non-free movie poster}}</text>
      <sha1>0xwxbtryeyzrmbe5ojeil2upovb6lzp</sha1>
      <model>wikitext</model>
      <format>text/x-wiki</format>
    </revision>
  </page>
  <page>
    <title>Qiwñaqocha</title>
    <ns>0</ns>
    <id>41535356</id>
    <redirect title="Qiwñaqucha" />
    <revision>
      <id>588932564</id>
      <timestamp>2014-01-03T06:06:25Z</timestamp>
      <contributor>
        <username>CaTi0604</username>
        <id>1509060</id>
      </contributor>
      <comment>[[WP:AES|←]]Redirected page to [[Qiwñaqucha]]</comment>
      <text xml:space="preserve">#REDIRECT[[Qiwñaqucha]]</text>
      <sha1>2k1ru4isq311ncnjruvgplv1jh4ccge</sha1>
      <model>wikitext</model>
      <format>text/x-wiki</format>
    </revision>
  </page>
  <page>
    <title>Template:Fb round2 2015 ACL 2QR</title>
    <ns>10</ns>
    <id>41535360</id>
    <revision>
      <id>588932742</id>
      <parentid>588932709</parentid>
      <timestamp>2014-01-03T06:07:59Z</timestamp>
      <contributor>
        <username>Weka</username>
        <id>1426266</id>
      </contributor>
      <text xml:space="preserve">[[2015 AFC Champions League#Round 2|2015 AFC Champions League 2nd qualifying round]]</text>
      <sha1>2h8hsszrn4a0zagp89xdudnc3qfkm9a</sha1>
      <model>wikitext</model>
      <format>text/x-wiki</format>
    </revision>
  </page>
  <page>
    <title>הלל סלובק</title>
    <ns>0</ns>
    <id>41535361</id>
    <redirect title="Hillel Slovak" />
    <revision>
      <id>588932615</id>
      <timestamp>2014-01-03T06:06:50Z</timestamp>
      <contributor>
        <username>Hoops gza</username>
        <id>11079571</id>
      </contributor>
      <comment>[[WP:AES|←]]Redirected page to [[Hillel Slovak]]</comment>
      <text xml:space="preserve">#REDIRECT [[Hillel Slovak]]</text>
      <sha1>i3tffa8n8tbmxi15dilh86kusg1eqro</sha1>
      <model>wikitext</model>
      <format>text/x-wiki</format>
    </revision>
  </page>
  <page>
    <title>Q'umirqocha (Camanti)</title>
    <ns>0</ns>
    <id>41535363</id>
    <redirect title="Q&#039;umirqucha (Camanti)" />
    <revision>
      <id>588932665</id>
      <timestamp>2014-01-03T06:07:15Z</timestamp>
      <contributor>
        <username>CaTi0604</username>
        <id>1509060</id>
      </contributor>
      <comment>[[WP:AES|←]]Redirected page to [[Q'umirqucha (Camanti)]]</comment>
      <text xml:space="preserve">#REDIRECT[[Q'umirqucha (Camanti)]]</text>
      <sha1>p02ulm0sy91dp6vlrdb4u30fycr36h0</sha1>
      <model>wikitext</model>
      <format>text/x-wiki</format>
    </revision>
  </page>
  <page>
    <title>Q'umirqocha (Ocongate)</title>
    <ns>0</ns>
    <id>41535366</id>
    <redirect title="Q&#039;umirqucha (Ocongate)" />
    <revision>
      <id>588932758</id>
      <timestamp>2014-01-03T06:08:08Z</timestamp>
      <contributor>
        <username>CaTi0604</username>
        <id>1509060</id>
      </contributor>
      <comment>[[WP:AES|←]]Redirected page to [[Q'umirqucha (Ocongate)]]</comment>
      <text xml:space="preserve">#REDIRECT[[Q'umirqucha (Ocongate)]]</text>
      <sha1>fnpyu9s5ah89i0q1kdxp0licxmaf8wu</sha1>
      <model>wikitext</model>
      <format>text/x-wiki</format>
    </revision>
  </page>
  <page>
    <title>Sona topaz tower</title>
    <ns>0</ns>
    <id>41535367</id>
    <redirect title="Sona Topaz Tower" />
    <revision>
      <id>588932782</id>
      <timestamp>2014-01-03T06:08:20Z</timestamp>
      <contributor>
        <username>WereSpielChequers</username>
        <id>4071608</id>
      </contributor>
      <comment>WereSpielChequers moved page [[Sona topaz tower]] to [[Sona Topaz Tower]]: caps plz</comment>
      <text xml:space="preserve">#REDIRECT [[Sona Topaz Tower]]
{{R from move}}</text>
      <sha1>ngogctu1cygz033hjz59snlbed1eyn2</sha1>
      <model>wikitext</model>
      <format>text/x-wiki</format>
    </revision>
  </page>
  <page>
    <title>Slovak, Hillel</title>
    <ns>0</ns>
    <id>41535369</id>
    <redirect title="Hillel Slovak" />
    <revision>
      <id>588932803</id>
      <timestamp>2014-01-03T06:08:27Z</timestamp>
      <contributor>
        <username>Hoops gza</username>
        <id>11079571</id>
      </contributor>
      <comment>[[WP:AES|←]]Redirected page to [[Hillel Slovak]]</comment>
      <text xml:space="preserve">#REDIRECT [[Hillel Slovak]]</text>
      <sha1>i3tffa8n8tbmxi15dilh86kusg1eqro</sha1>
      <model>wikitext</model>
      <format>text/x-wiki</format>
    </revision>
  </page>
  <page>
    <title>Hilel Slovak</title>
    <ns>0</ns>
    <id>41535370</id>
    <redirect title="Hillel Slovak" />
    <revision>
      <id>588932819</id>
      <timestamp>2014-01-03T06:08:39Z</timestamp>
      <contributor>
        <username>Hoops gza</username>
        <id>11079571</id>
      </contributor>
      <comment>[[WP:AES|←]]Redirected page to [[Hillel Slovak]]</comment>
      <text xml:space="preserve">#REDIRECT [[Hillel Slovak]]</text>
      <sha1>i3tffa8n8tbmxi15dilh86kusg1eqro</sha1>
      <model>wikitext</model>
      <format>text/x-wiki</format>
    </revision>
  </page>
  <page>
    <title>Slovak, Hilel</title>
    <ns>0</ns>
    <id>41535372</id>
    <redirect title="Hillel Slovak" />
    <revision>
      <id>588932852</id>
      <timestamp>2014-01-03T06:09:00Z</timestamp>
      <contributor>
        <username>Hoops gza</username>
        <id>11079571</id>
      </contributor>
      <comment>[[WP:AES|←]]Redirected page to [[Hillel Slovak]]</comment>
      <text xml:space="preserve">#REDIRECT [[Hillel Slovak]]</text>
      <sha1>i3tffa8n8tbmxi15dilh86kusg1eqro</sha1>
      <model>wikitext</model>
      <format>text/x-wiki</format>
    </revision>
  </page>
  <page>
    <title>WKKD (AM)</title>
    <ns>0</ns>
    <id>41535373</id>
    <revision>
      <id>588932864</id>
      <timestamp>2014-01-03T06:09:09Z</timestamp>
      <contributor>
        <username>Tdl1060</username>
        <id>646386</id>
      </contributor>
      <comment>created article</comment>
      <text xml:space="preserve">{{Infobox Radio Station |
  image            = |
  name             = WKKD|
  frequency        = 1580 [[AM radio|AM]] ([[kilohertz|kHz]])|
  city             = [[Aurora, Illinois]]|
  airdate          = 1960|
  area             = |
  format           = |
  owner            = |
  facility_id      = |
  power            = 170 [[watt]]s day&lt;br&gt;200 watts night|
  erp              = |
  haat             = |
  branding         = |
  slogan           = |
  class            = |
  former_callsigns = WKKD, WFVR|
  webcast          = |
  website          = |
  callsign_meaning = '''W'''ill, '''K'''ane, '''K'''endall and '''D'''uPage|
  sister_stations  = |
}}
'''WKKD''' 1580 [[AM broadcasting|AM]] was a [[radio station]] licensed to [[Aurora, Illinois]].  The station began broadcasting in 1960 and initially ran 250 watts during daytime hours only with a directional pattern towards Aurora.&lt;ref name=&quot;Valley&quot;&gt;Ghrist, John R. &quot;Valley Voices: A Radio History&quot; 1996. (p. 106)&lt;/ref&gt;

The station began simulcasting on 95.9 [[WERV-FM|WKKD-FM]] in 1961. The stations initially aired a [[Full service (radio format)|full service]] format that focused heavily on [[Country music]],&lt;ref&gt;[http://books.google.com/books?id=CiEEAAAAMBAJ&amp;pg=PA8&amp;dq=WKKD+Aurora&amp;as_pt=MAGAZINES&amp;cd=1#v=onepage&amp;q=WKKD%20Aurora&amp;f=false Folk Talent &amp; Tunes] Sachs, Bill. (p. 8) Billboard. July 10, 1961. Accessed January 2, 2014&lt;/ref&gt;&lt;ref&gt;[http://books.google.com/books?id=fR8EAAAAMBAJ&amp;pg=PA38&amp;dq=WKKD+Aurora&amp;as_pt=MAGAZINES&amp;cd=5#v=onepage&amp;q=WKKD%20Aurora&amp;f=false Folk Talent &amp; Tunes] Sachs, Bill. (p. 38) Billboard. July 18, 1960. Accessed January 2, 2014&lt;/ref&gt;&lt;ref&gt;[http://books.google.com/books?id=uB8EAAAAMBAJ&amp;pg=PA47&amp;dq=WKKD+Aurora&amp;lr=&amp;as_pt=MAGAZINES&amp;cd=13#v=onepage&amp;q=WKKD%20Aurora&amp;f=false Folk Talent &amp; Tunes] Sachs, Bill. (p. 47) Billboard. May 16, 1960. Accessed January 2, 2014&lt;/ref&gt;&lt;ref&gt;[http://books.google.com/books?id=ew8EAAAAMBAJ&amp;pg=PA50&amp;dq=WKKD+Aurora&amp;as_pt=MAGAZINES&amp;cd=6#v=onepage&amp;q=WKKD%20Aurora&amp;f=false Nashville Scene] Whisenhunt, Elton. (p. 50) Billboard. February 5, 1966. Accessed January 2, 2014&lt;/ref&gt;

By the early 1970s the simulcast had ended with WKKD-FM adopting a [[Beautiful music]] format. AM 1580's callsign was changed to WFVR, and it continued to air the country music format.&lt;ref name=&quot;Valley&quot;/&gt; WFVR's format was later changed to [[Adult Contemporary]]-[[Middle of the road (music)|MOR]].&lt;ref&gt;[http://www.americanradiohistory.com/Archive-Station-Albums/Chicago-Trib-1979-Mar-About-Chi-Radio.pdf Stations, everywhere: a listeners' guide to the AM and FM bands] ''Chicago Tribune Magazine''. March 4, 1979. Accessed January 2, 2014&lt;/ref&gt;

In the early 1980s the station's callsign was changed back to WKKD and it again simulcast WKKD-FM. In the mid '80s the station began broadcasting during nightime hours. By the late 80s the simulcast had ended, and WKKD AM had begun airing an [[oldies]] format.&lt;ref&gt;[http://www.americanradiohistory.com/Archive-Other-Documments/Chicago_Magazine/Chicago-1989-Fall.pdf WKKD AM 1580] Radio Chicago. Fall 1989. (p. 18) Accessed January 2, 2014&lt;/ref&gt;&lt;ref&gt;[http://articles.chicagotribune.com/1990-02-25/features/9001170010_1_beasley-broadcast-group-format-big-band-station Radio In Du Page] Wilhelmson, Brenda. ''Chicago Tribune.'' February 25, 1990. Accessed January 2, 2014&lt;/ref&gt; In the early 1990s WKKD-FM began simulcasting the oldies format of WKKD AM, and the stations became known as &quot;Pure Gold 96&quot;&lt;ref name=&quot;Lettermen&quot;&gt;[http://articles.chicagotribune.com/1993-02-12/entertainment/9303180714_1_irish-rovers-concert-pure-gold Lettermen Bring Valentine Spirit To Norris] Todorovich, Lisa. ''Chicago Tribune.'' February 12, 1993. Accessed January 2, 2014&lt;/ref&gt; In March 1995, 1580 left the simulcast and began airing the [[Real Country]] [[country music]] format.&lt;ref&gt;[http://articles.chicagotribune.com/1995-03-26/features/9503260089_1_fm-oldies-station-music-director-and-assistant Reporters Have New Assignments On Ch. 2 Mission] Nidetz, Steve. ''Chicago Tribune''. March 26, 1995. Accessed January 2, 2014&lt;/ref&gt; On July 1, 1996, the station adopted a [[Spanish language]] [[Tejano music]] format as &quot;Viva 1580&quot;.&lt;ref&gt;[http://web.archive.org/web/19970414123243/http://www.wkkd.com/new.htm What's New @ WKKD Salter Broadcasting] wkkd.com. Internet Archive. April 14, 1997. Accessed January 2, 2014&lt;/ref&gt;&lt;ref&gt;[http://web.archive.org/web/19970414123147/http://www.wkkd.com/1580.htm VIVA 1580 HOT TEJANO RADIO] wkkd.com. Internet Archive. April 14, 1997. Accessed January 2, 2014&lt;/ref&gt; In 1997, the station's format changed to [[CNN Headline News]].&lt;ref&gt;[http://web.archive.org/web/19971010013308/http://www.wkkd.com/1580am/index.html WKKD AM 1580] wkkd.com. Internet Archive. October 10, 1997. Accessed January 2, 2014&lt;/ref&gt;

On January 1, 2002, the station was sold to Kovas Communications, and it began simulcasting the ethnic programming of [[WCGO|WONX]].&lt;ref&gt;[http://www.highbeam.com/doc/1N1-0EFF0020A5EB18D8.html WKKD sold to Kovas Broadcasting] The Beacon News. October 7, 2001. Accessed January 2, 2014&lt;/ref&gt; On January 31, 2005, the station adopted a &quot;Health Radio&quot; format, airing talk shows related to health, wellness and fitness.&lt;ref&gt;Feder, Robert. &quot;Station goes full time as 'Health Radio' outlet&quot;. ''Chicago Sun Times''. January 27, 2005&lt;/ref&gt; This format would later be simulcast on 1600 [[WMCW]]. In 2007, Kovas Communications applied with the FCC to move WKKD to [[Silvis, Illinois]].&lt;ref&gt;[http://qconline.com/archives/qco/print_display.php?id=367017 Health Radio files for move to Silvis] ''Quad Cities Dispatch Argus''. December 18, 2007. Accessed January 2, 2014&lt;/ref&gt; In February 2008, the station was granted a construction permit to move WKKD to [[Silvis, Illinois]], and increase its power to 1,000 watts during the day and 1,400 watts at night.&lt;ref&gt;[http://qctimes.com/business/chicago-radio-station-may-move-to-silvis/article_d7b9dce8-64f9-5cb4-8bd1-d3c6068beceb.html Chicago radio station may move to Silvis] Burke, David. ''Quad City Business Journal''. February 25, 2008. Accessed January 2, 2014&lt;/ref&gt; In 2009, the station was taken off the air and Kovas Communications surrendered the station's license to the FCC.&lt;ref&gt;[http://ndb.at.ua/_ld/0/18_may_june09_enc.pdf Call Letter Changes] ''Medium Wave News''. May/June 2009. (p. 11) Accessed January 2, 2014&lt;/ref&gt;

==References==
{{reflist}}

{{Chicago Radio}}

[[Category:Defunct radio stations in the United States]]
[[Category:Radio stations established in 1960]]
[[Category:Radio stations disestablished in 2009]]
[[Category:Radio stations in Illinois|KKD]]</text>
      <sha1>9vmv1pm881tuv3by10wktfnawsdzn9r</sha1>
      <model>wikitext</model>
      <format>text/x-wiki</format>
    </revision>
  </page>
  <page>
    <title>Mount Q'umirqocha (Peru)</title>
    <ns>0</ns>
    <id>41535376</id>
    <redirect title="Mount Q&#039;umirqucha (Peru)" />
    <revision>
      <id>588932909</id>
      <timestamp>2014-01-03T06:09:36Z</timestamp>
      <contributor>
        <username>CaTi0604</username>
        <id>1509060</id>
      </contributor>
      <comment>[[WP:AES|←]]Redirected page to [[Mount Q'umirqucha (Peru)]]</comment>
      <text xml:space="preserve">#REDIRECT[[Mount Q'umirqucha (Peru)]]</text>
      <sha1>jicv5xjkn87ug449xuoofjlzlmq4oqr</sha1>
      <model>wikitext</model>
      <format>text/x-wiki</format>
    </revision>
  </page>
  <page>
    <title>Mixed Martial Arts in Australia</title>
    <ns>0</ns>
    <id>41535377</id>
    <redirect title="Mixed martial arts in Australia" />
    <revision>
      <id>588932920</id>
      <timestamp>2014-01-03T06:09:40Z</timestamp>
      <contributor>
        <username>Ianblair23</username>
        <id>145927</id>
      </contributor>
      <comment>Ianblair23 moved page [[Mixed Martial Arts in Australia]] to [[Mixed martial arts in Australia]]: lowercase</comment>
      <text xml:space="preserve">#REDIRECT [[Mixed martial arts in Australia]]
{{R from move}}</text>
      <sha1>7w5zr85fbbiqv29uxb8cg2h9vhzrajh</sha1>
      <model>wikitext</model>
      <format>text/x-wiki</format>
    </revision>
  </page>
  <page>
    <title>Q'umirqocha (Q'umir Qocha)</title>
    <ns>0</ns>
    <id>41535381</id>
    <redirect title="Q&#039;umirqucha (Q&#039;umir Qucha)" />
    <revision>
      <id>588932989</id>
      <timestamp>2014-01-03T06:10:18Z</timestamp>
      <contributor>
        <username>CaTi0604</username>
        <id>1509060</id>
      </contributor>
      <comment>[[WP:AES|←]]Redirected page to [[Q'umirqucha (Q'umir Qucha)]]</comment>
      <text xml:space="preserve">#REDIRECT[[Q'umirqucha (Q'umir Qucha)]]</text>
      <sha1>nbfmo1jj1m4djw5kiv489phe9rg69vq</sha1>
      <model>wikitext</model>
      <format>text/x-wiki</format>
    </revision>
  </page>
  <page>
    <title>Frusciante, John</title>
    <ns>0</ns>
    <id>41535384</id>
    <redirect title="John Frusciante" />
    <revision>
      <id>588933051</id>
      <timestamp>2014-01-03T06:10:52Z</timestamp>
      <contributor>
        <username>Hoops gza</username>
        <id>11079571</id>
      </contributor>
      <comment>[[WP:AES|←]]Redirected page to [[John Frusciante]]</comment>
      <text xml:space="preserve">#REDIRECT [[John Frusciante]]</text>
      <sha1>dylr6nfscazgocmhvrb8lixtpvhinwg</sha1>
      <model>wikitext</model>
      <format>text/x-wiki</format>
    </revision>
  </page>
  <page>
    <title>Q'umirqocha (Yanaq Qusqu K'uchu)</title>
    <ns>0</ns>
    <id>41535385</id>
    <redirect title="Q&#039;umirqucha (Yanaq Qusqu K&#039;uchu)" />
    <revision>
      <id>588933065</id>
      <timestamp>2014-01-03T06:11:00Z</timestamp>
      <contributor>
        <username>CaTi0604</username>
        <id>1509060</id>
      </contributor>
      <comment>[[WP:AES|←]]Redirected page to [[Q'umirqucha (Yanaq Qusqu K'uchu)]]</comment>
      <text xml:space="preserve">#REDIRECT[[Q'umirqucha (Yanaq Qusqu K'uchu)]]</text>
      <sha1>l7xqyxeqzr36hqrf2yekjfncs4gcy23</sha1>
      <model>wikitext</model>
      <format>text/x-wiki</format>
    </revision>
  </page>
</mediawiki>